{
  "place": "",
  "tags": [
    "content.press.books.title"
  ],
  "sections": [
    {
      "title": "",
      "imgs": [
        "books/1.jpg",
        "books/2.jpg",
        "books/3.jpg",
        "books/4.jpg",
        "books/5.jpg",
        "books/6.jpg",
        "books/7.jpg",
        "books/8.jpg",
        "books/9.jpg",
        "books/10.jpg",
        "books/11.jpg",
        "books/12.jpg",
        "books/13.jpg",
        "books/14.jpg",
        "books/15.jpg",
        "books/16.jpg",
        "books/17.jpg",
        "books/18.jpg"
      ]
    }
  ]
}